number_booster/__init__.py
number_booster/base.py
number_booster/fixed.py
number_booster/random.py
number_booster-0.1.0.dist-info/LICENSE
number_booster-0.1.0.dist-info/METADATA
number_booster-0.1.0.dist-info/WHEEL
number_booster-0.1.0.dist-info/RECORD
