Metadata-Version: 2.3
Name: number-booster
Version: 0.1.0
Summary: A flexible Python library for boosting numeric values using the Strategy pattern. Designed for blockchain transactions to flexibly increase gas and gasPrice.
License: MIT
Author: Roman505050
Author-email: myhun59@gmail.com
Requires-Python: >=3.9
Classifier: License :: OSI Approved :: MIT License
Classifier: Programming Language :: Python :: 3
Classifier: Programming Language :: Python :: 3.9
Classifier: Programming Language :: Python :: 3.10
Classifier: Programming Language :: Python :: 3.11
Classifier: Programming Language :: Python :: 3.12
Classifier: Programming Language :: Python :: 3.13
